shacko/__init__.py
shacko/py.typed
shacko-0.3.2.dist-info/METADATA
shacko-0.3.2.dist-info/WHEEL
shacko-0.3.2.dist-info/RECORD
