Metadata-Version: 2.3
Name: shacko
Version: 0.3.2
Summary: Shacko: The Digital Homeless Framework. Tested in the toughest times. ✅
Project-URL: Repository, https://github.com/homeless-framework/homeless
Requires-Python: >=3.12
